minirl/__init__.py
minirl/bayes/gaussianNaiveBayes.py
minirl/vit/__init__.py
minirl/vit/components/engine.py
minirl/vit/main.py
minirl/vit/network/attention.py
minirl/vit/network/embedding.py
minirl/vit/network/mlp.py
minirl/vit/network/transformer.py
minirl/vit/network/vit.py
minirl-0.0.2.dist-info/METADATA
minirl-0.0.2.dist-info/WHEEL
minirl-0.0.2.dist-info/RECORD
