Metadata-Version: 2.1
Name: minirl
Version: 0.0.2
Summary: minirl - RL for Robot
License: LICENSE
Author: Nicolasalan
Author-email: grottimeireles@gmail.com
Requires-Python: >=3.10,<4.0
Classifier: License :: Other/Proprietary License
Classifier: Programming Language :: Python :: 3
Classifier: Programming Language :: Python :: 3.10
Classifier: Programming Language :: Python :: 3.11
Classifier: Programming Language :: Python :: 3.12
Requires-Dist: lightning (>=2.2.0,<3.0.0)
Requires-Dist: matplotlib (>=3.4.3,<4.0.0)
Requires-Dist: numpy (>=1.24.2,<2.0.0)
Requires-Dist: torch (>=2.0.1,<3.0.0)
Requires-Dist: torchinfo (>=1.5.2,<2.0.0)
Requires-Dist: torchvision (>=0.17.2,<0.18.0)
Project-URL: bugs, https://github.com/minirl/minirl/issues
